MANIFEST.in
README
setup.py
bin/b2x
bin/bi2x
buml/__init__.py
buml/baseNodes.py
buml/baseWriterNodes.py
buml/bumlParser.py
buml/inlineMapper.py
buml/inlineParser.py
buml/mappingSpec.py
buml/nodeFactory.py
buml/rstParser.py
buml/transformUtils.py
buml/utilities.py
buml.egg-info/PKG-INFO
buml.egg-info/SOURCES.txt
buml.egg-info/dependency_links.txt
buml.egg-info/top_level.txt
buml.egg-info/zip-safe
docs/architecture.rst
docs/bnf.rst
docs/buml.diag
docs/buml.png
docs/bundledInlineParser.rst
docs/cli.rst
docs/demo.rst
docs/index.rst
docs/interactive.rst
docs/logoCropped.png
docs/transformations.rst
docs/writerConfig.rst
testData/demo.buml
tests/__init__.py
tests/test-all.py
tests/test-baseNodes.py
tests/test-baseWriterNodes.py
tests/test-bumlParser.py
tests/test-inlineMapper.py
tests/test-inlineParser.py
tests/test-mappingSpec.py
tests/test-utilities.py