Metadata-Version: 1.0
Name: buml
Version: 0.1.4
Summary: buml markup language
Home-page: http://bruegger.it/buml/
Author: Bud P. Bruegger
Author-email: bud@bruegger.it
License: FreeBSD
Keywords: buml xml html nodeTree shpaml template
Platform: UNKNOWN
Classifier: Development Status :: 4 - Beta
Classifier: Environment :: Console
Classifier: Environment :: Web Environment
Classifier: Intended Audience :: Developers
Classifier: License :: OSI Approved :: BSD License
Classifier: Operating System :: OS Independent
Classifier: Programming Language :: Python
Classifier: Programming Language :: Python :: 2.7
Classifier: Topic :: Text Processing :: Markup
Classifier: Topic :: Text Processing :: Markup :: XML
Classifier: Topic :: Text Processing :: Markup :: HTML
Classifier: Topic :: Text Processing
